Metadata-Version: 2.1
Name: hanzipy
Version: 1.0.4
Summary: Hanzi decomposition and dictionary
Home-page: https://github.com/Synkied/hanzipy
Download-URL: https://github.com/Synkied/hanzipy/archive/1.0.4.tar.gz
Author: 昆汀
Author-email: synkx@hotmail.fr
Keywords: python,hanzi,hanzipy,decomposition,cjk,dictionary
Classifier: Development Status :: 4 - Beta
Classifier: Intended Audience :: Developers
Classifier: License :: OSI Approved :: MIT License
Classifier: Programming Language :: Python :: 3
Classifier: Operating System :: MacOS :: MacOS X
Classifier: Operating System :: Microsoft :: Windows
Classifier: Operating System :: POSIX
Provides-Extra: dev
Provides-Extra: dev-test
License-File: LICENSE
